{
  "files": {
    "packages/backend/.turbo/turbo-build.log": {
      "size": 27679,
      "mtime_nanos": 1783734316972554551,
      "mode": 436,
      "is_dir": false
    },
    "packages/backend/dist": {
      "size": 0,
      "mtime_nanos": 0,
      "mode": 0,
      "is_dir": true
    },
    "packages/backend/dist/skeleton.tar.gz": {
      "size": 1977,
      "mtime_nanos": 1783734316407999000,
      "mode": 436,
      "is_dir": false
    },
    "packages/backend/dist/bundle.tar.gz": {
      "size": 6893541,
      "mtime_nanos": 1783734316904554397,
      "mode": 436,
      "is_dir": false
    }
  },
  "order": [
    "packages/backend/.turbo/turbo-build.log",
    "packages/backend/dist",
    "packages/backend/dist/bundle.tar.gz",
    "packages/backend/dist/skeleton.tar.gz"
  ]
}
